LICENSE
MANIFEST.in
README.md
README.rst
setup.cfg
setup.py
payments/__init__.py
payments/manage.py
payments/docs/documentation
payments/payments/__init__.py
payments/payments/admin.py
payments/payments/apps.py
payments/payments/models.py
payments/payments/recursive_searcher.py
payments/payments/tests.py
payments/payments/urls.py
payments/payments/views.py
payments/payments/migrations/__init__.py
payments/rent_insider_payments/__init__.py
payments/rent_insider_payments/asgi.py
payments/rent_insider_payments/settings.py
payments/rent_insider_payments/urls.py
payments/rent_insider_payments/wsgi.py
payments/subscriptions/__init__.py
payments/subscriptions/admin.py
payments/subscriptions/apps.py
payments/subscriptions/models.py
payments/subscriptions/tests.py
payments/subscriptions/urls.py
payments/subscriptions/views.py
payments/subscriptions/migrations/__init__.py
payments/webhooks/__init__.py
payments/webhooks/admin.py
payments/webhooks/apps.py
payments/webhooks/models.py
payments/webhooks/tests.py
payments/webhooks/urls.py
payments/webhooks/views.py
payments/webhooks/migrations/__init__.py
payments_romania.egg-info/PKG-INFO
payments_romania.egg-info/SOURCES.txt
payments_romania.egg-info/dependency_links.txt
payments_romania.egg-info/requires.txt
payments_romania.egg-info/top_level.txt
venv/__init__.py
venv/bin/__init__.py
venv/lib/__init__.py